pyuavlink/__init__.py
pyuavlink/cli.py
pyuavlink/pyuavlink.py
pyuavlink-0.1.2.dist-info/licenses/AUTHORS.rst
pyuavlink-0.1.2.dist-info/licenses/LICENSE
pyuavlink-0.1.2.dist-info/METADATA
pyuavlink-0.1.2.dist-info/WHEEL
pyuavlink-0.1.2.dist-info/top_level.txt
pyuavlink-0.1.2.dist-info/RECORD
