Metadata-Version: 2.4
Name: pyuavlink
Version: 0.1.2
Summary: A Python library for UAV-to-UAV communication over V2X/D2D, optimized for dynamic networks and ns-3-dev integration.
Author-email: Jing Xiang Yu <yujx.res@gmail.com>
Maintainer-email: Jing Xiang Yu <yujx.res@gmail.com>
License-Expression: GPL-3.0-or-later
Project-URL: bugs, https://github.com/YUJX19/pyuavlink/issues
Project-URL: changelog, https://github.com/YUJX19/pyuavlink/blob/master/changelog.md
Project-URL: homepage, https://github.com/YUJX19/pyuavlink
Requires-Python: <3.11,>=3.7
License-File: LICENSE
License-File: AUTHORS.rst
Requires-Dist: typer
Requires-Dist: psutil>=5.8.0
Requires-Dist: rich
Provides-Extra: dev
Requires-Dist: coverage; extra == "dev"
Requires-Dist: mypy; extra == "dev"
Requires-Dist: pytest; extra == "dev"
Requires-Dist: ruff; extra == "dev"
Dynamic: license-file
